{
  "number": 95,
  "language": "luo",
  "title": "95 Jarit, Go Tung` Mar Injili",
  "stanzas": [
    {
      "type": "verse",
      "lines": [
        "1. Jarit, go tung` mar Injili,Mond` inyis ji duto wach;Ma ka ng`ato osewinjo,Olokre ni mond` okwo."
      ],
      "number": 1
    },
    {
      "type": "verse",
      "lines": [
        "Jarit, go tung` mar Injili,Ka igoye gi teko;Nyasachi e mosechiki,Jo motwe giyud thuolo."
      ],
      "number": 2
    },
    {
      "type": "verse",
      "lines": [
        "2. Mond` igoye e wi gode,Kendo e pewe duto;Kwonde duto, e ru ler duto,Mondo giwinj Injili."
      ],
      "number": 3
    },
    {
      "type": "verse",
      "lines": [
        "3. Kendo igoye e gwenge,Kod wang`yore duto te;Mond` iland wach ni ji duto,Kaka Wuoro luongogi."
      ],
      "number": 4
    },
    {
      "type": "verse",
      "lines": [
        "4. Jogo be ma ting` ohewo,Magombo yudo thuolo;Nyisgi kaka Ruoth Jawarwa,Wacho, \"Biuru ira.\""
      ],
      "number": 5
    }
  ]
}