{
  "number": 331,
  "language": "ny",
  "title": "331 - Tamani Mlungu Mtimamo",
  "stanzas": [
    {
      "type": "verse",
      "lines": [
        "PRAISE THE LORD, O MY SOUL"
      ],
      "number": 1
    },
    {
      "type": "chorus",
      "lines": [
        "1. Tamani Mlungu mtimamo, Wakundifera pansipo,",
        "Nafafaniza chimolo, Nanditengera dipole.",
        "CHORUS:",
        "Wandiombola inetu, Potaya mwazi wacewo",
        "Timlemekeza Iyetu, Wotipilira dipole",
        "2. Ndinasocera kalelo, Ndamkana Iye Yesuyo",
        "Koma ndiyimba leroli, Wandiombola inedi.",
        "3. Cikondwerero ciripo, Popenyetsetsa Yesuyo,",
        "Pa mtanda pace pomwepo, Pakundifera inenso.",
        "4. Ndiribe ntchito zangazo, Kukoma Mtima wangawo",
        "Anandiyesa inetu, Wakulungama Yesuyo.",
        "5. Tsono mubwere inunso, Mombolo wanu ndiyedi",
        "Apulumutsa onsewo, Okhulupira Yesuyo."
      ]
    }
  ]
}