{
  "number": 44,
  "language": "ny",
  "title": "44 - Ndidzamdziwa Mombolo Wanga",
  "stanzas": [
    {
      "type": "verse",
      "lines": [
        "WHEN MY LIFE-WORK IS ENDED"
      ],
      "number": 1
    },
    {
      "type": "chorus",
      "lines": [
        "1. Pamene nditatha zintchito zanga zonsezo,",
        "Nditaoloka pa tsidya la nyanja;",
        "Chakufachi chikadzavalatu chosafanso;",
        "Pompo ndidzamdziwa Mombolo wanga.",
        "CHORUS:",
        "Ndidzamdziwa, Ndidzamdziwa, Podzaima pa mbali pakepo,",
        "Ndidzamdziwa, ndidzamdziwa, Ndi misomali m’manja mwake.",
        "2. Moyo wanga udzakondwera pakumuona,",
        "Ndi kuona nkhope yake yowala;",
        "Ndidzamyamika Iye ndi mtima wanga wonse,",
        "Malo adandikonzera kumwamba.",
        "3. Ee! ndidzakondwa pakuona okondedwawo",
        "Omwe ndalekana nawo m’dzikoli;",
        "Koma n’dzayamba ndaonana naye Yesuyo,",
        "Wokondedwa wanga wopambanayo.",
        "4. Kupyolera pa zipata kunka ku mzindawo,",
        "Iye adzanditsogolera ine,",
        "Nyimbo ya nthawi zonse ndidzayimba mokondwa;",
        "Nditamuona Mpulumutsi wanga."
      ]
    }
  ]
}