{
  "number": 209,
  "language": "bem",
  "title": "209 - APEPI NANKWE",
  "stanzas": [
    {
      "type": "verse",
      "lines": [
        "O FOR A CLOSER WALK"
      ],
      "number": 1
    },
    {
      "type": "verse",
      "lines": [
        "1. Ukwenda pepi na Lesa,",
        "E nshila ya ku mu-lu;",
        "Lubuto lubushe nshila-,",
        "Yakuya ku Mfumu.",
        "2. Bwela Mupa-shi Wa-shila,",
        "We ntu-mi i-ya ci-ne;",
        "Nali pato bubi pantu-,",
        "Bufumya ku-li 'Mwe",
        "3. Kwali nshita shamu-tende,",
        "Ndatemwe lyo njibu-sha;",
        "Shali-ya nsha-kashi-sange,",
        "Muli cino calo.",
        "4. Aka-lubi nate-mwisha,",
        "Nangu kabe shani-,",
        "Ngafwa kafu-me ku-li 'ne-,",
        "Nshale fye na Imwe."
      ],
      "number": 2
    }
  ]
}