{
  "number": 43,
  "language": "bem",
  "title": "43 - TULO TWAPALWA",
  "stanzas": [
    {
      "type": "verse",
      "lines": [
        "ASLEEP IN JESUS"
      ],
      "number": 1
    },
    {
      "type": "verse",
      "lines": [
        "1. Tulo twapalwa, twapalwa,",
        "Ukulila konse kwapwa;",
        "Ukulala utulo fye,",
        "Amacusho yonse yapwa.",
        "CHORUS:",
        "Tulo twapalwa, cawama,",
        "Ukuteyanya kul’ici:",
        "Kutusha mu busumino,",
        "Ukupalwa inshiku pe.",
        "2. Tulo twapalwa, twapalwa,",
        "Kubuka pamo kwapalwa:",
        "Lintu Katula akesa,",
        "Tulo tukapwa munshinshi.",
        "3. Tulo twapalwa. twapalwa,",
        "Yesu, Katula akesa;",
        "Ukonaula imfwa pe",
        "Bakema mucishifwa pe."
      ],
      "number": 2
    }
  ]
}