{
  "number": 494,
  "language": "tw",
  "title": "\"Yebehu Yesu\", 'Fisɛ Sunsuma Nyin",
  "stanzas": [
    {
      "type": "verse",
      "lines": [
        "\\\"Yebehu Yesu\\\", 'fisɛ sunsuma nyin",
        "Tware ɔbra kwan ketewa no mu,",
        "Yebehu Yesu, ná ahyɛ yɛn gyidi den",
        "ɔbra yi mu ko a etwa to nom'."
      ],
      "number": 1
    },
    {
      "type": "verse",
      "lines": [
        "\\\"Yebehu Yesu\\\", yɛn nkwagye Botan no",
        "Faako a wɔde dom gu yɛn nan 'se;",
        "Nɔkwa, owu ne mu anib're nyinaa",
        "Rentumi ntwe yɛn mfi N'anim hwɛ ho."
      ],
      "number": 2
    },
    {
      "type": "verse",
      "lines": [
        "\\\"Yebehu Yesu\\\", akanea fof'ro a",
        "Y'ani agye ho mfe pii no redum;",
        "Bɔne wiase yi my nhyira di huammɔ",
        "Yerenni ho yaw mfa nsesa Wo da."
      ],
      "number": 3
    },
    {
      "type": "verse",
      "lines": [
        "\\\"Yebehu Yesu\\\", eyi ne yɛn 'hiade,",
        "'Hoɔden, 'nigye, ɔpɛ de 'dehu ba;",
        "Yebehu Yesu, Wawu asɔr' resrɛ",
        "Sɛ ɔreba bewie saa 'nadwo yi."
      ],
      "number": 4
    }
  ]
}