{
  "number": 263,
  "language": "en",
  "title": "263 “Bring Ye All The Tithes.”",
  "stanzas": [
    {
      "type": "verse",
      "lines": [
        "Hear the words of Scripture from the ages past,",
        "“Bring ye all the tithes into the store-house,”",
        "Make a consecration that will ever last,",
        "Trusting for the promised blessing."
      ],
      "number": 1
    },
    {
      "type": "chorus",
      "lines": [
        "“Bring ye all the tithes into the store-house,",
        "And prove me now,” saith the Lord of hosts;",
        "And I will pour out a blessing,",
        "There shall not be room enough to receive it.”"
      ]
    },
    {
      "type": "verse",
      "lines": [
        "Do you seek to know the Holy Spirit’s power?",
        "“Bring ye all the tithes into the store-house,”",
        "Live in sweet communion with Him hour by hour,",
        "While He give the promised blessing"
      ],
      "number": 2
    },
    {
      "type": "verse",
      "lines": [
        "Is there aught that stands between you and your Lord?",
        "“Bring ye all the tithes into the store-house,",
        "Bring them on conditions promised in His word,",
        "And He’ll pour you out a blessing."
      ],
      "number": 3
    },
    {
      "type": "verse",
      "lines": [
        "Lift your heart this moment, claim Him Lord and King,",
        "As ye bring the tithes into the store-house;",
        "Trust the blessed promise, and your praise shall ring,",
        "From the heart He is possessing."
      ],
      "number": 4
    },
    {
      "type": "verse",
      "lines": [
        "Let the anthems roll in grandeur thro’ the skies,",
        "Having brought the tithes into the store-house;",
        "Joyous hallelujahs from our hearts arise,",
        "For we have the promised blessing."
      ],
      "number": 5
    }
  ]
}