{
  "number": 264,
  "language": "to",
  "title": "264: BUZUBA BUSALALA",
  "stanzas": [
    {
      "type": "verse",
      "lines": [
        "AH 381CH 654264BUZUBA BUSALALA",
        "HOLY DAY JEHOVAH&#213;S REST",
        "Doh is G",
        "1",
        "Buzuba busalala, Bwa mvwiki ya kulenga",
        "Bumaninzya imvwiki, Leza watupa tonse.",
        "CIINDULULO:",
        "Bola, bola, bola, bola, Buzuba bwa nSabata,",
        "(Bola, bola, bola, bola, bola, bola, bola, bola)",
        "Leza wa buleleka.",
        "2",
        "Mazuba cisambomwe, Wakamana mulilo,",
        "Buzuba bwa ciloba, Twa lyokezya anguwe.",
        "3",
        "Banji babusandula, Bakomba mubutanzi,",
        "Jula Bbuku uzyibe, Baibele lya kaka.",
        "4",
        "Bazyi kasimpe bati, Muntu wa busandula,",
        "Kuzwa ku malemgelo, nSabata njiya Mwami.",
        "5",
        "Nenda yiya mwi Bbuku, Ndazyiba I nSabata,",
        "Elyo nda mucilila, Kunyina nzila imbi."
      ],
      "number": 1
    }
  ]
}