{
  "number": 29,
  "language": "ts",
  "title": "29. XWANA HOSI HIKUVA RI HLWILE",
  "stanzas": [
    {
      "type": "verse",
      "lines": [
        "ABIDE WITH ME",
        "1. Xwana Hosi Hikuva Ri Hlwile, Ni Vusiku Byi Endle Vu Nyama;",
        "Ku Hava Mpfuna Na Khongomelo, Ndzi Pfuxe Xwana Na Mina Yesu.",
        "2. Vutomi Byi Hatlisa Ku Hundza, Ntsako Na Byo Vumburhi Swa Hela;",
        "Leswo Hanya Swi Mbala Ku Bola, La Nga Hundzukiki Xwana Kwala.",
        "3. Nkarhi Hinkwawo, Tshama Na Mina, Nsovo Waku Wu Hlula Miringo;",
        "Hi Wena Ntsena La Hlayisaka, Nkarhi Hinkwawo Xwana Na Mina.",
        "4. Hambi Khombo Minkosi, Nhlomulo, Na Ro Rifu Rahi Bvanyangeta,",
        "Hi Ta Pfuxiwa Hiri Vahluri, Loko Uxwa Na Mina We Hosi.",
        "5. Loko Nkarhi Wa Mina Wu Ta Ta. Wa Ku Rhurha Ndzi Siya Misava;",
        "Nta Kuma Mani Loka Nga Ri Wena, Xwana Yesu U Tshama Na Mina."
      ],
      "number": 1
    }
  ]
}