{
  "number": 93,
  "language": "rw",
  "title": " 93 N'Umunsi Wera Wo Kuruhuka",
  "stanzas": [
    {
      "type": "verse",
      "lines": [
        "### 93 N'Umunsi Wera Wo Kuruhuka",
        "**1**",
        "N'umunsi wera wo kuruhuka,",
        "Muns'uhiriwe w'amahoro;",
        "Ukiz'intebyi n'ufit'ishavu,",
        "Mwiz'ushimwa mu yindi yose.",
        "Mwami mur'uwo munsi,",
        "Bose bagusingiza,",
        "Ngo weze, weze, weze,",
        "Kukw'ariw'uhorahw'iteka.",
        "**2**",
        "N'icyambu kibamw'ituza ryinshi,",
        "Ntikibamw'imidugararo.",
        "Ni nk'umurima w'Iparadiso,",
        "Imigezi myiz'inyuramo.",
        "Usa n'isokw'ifuka,",
        "Iy'amapfa yacanye.",
        "Ni nkaho tubonera,",
        "Igihugu cy'isezerano.",
        "**3**",
        "N'umunsi twongerwamw'imbaraga,",
        "N'umuns'uduter'urukundo.",
        "Ni w'utuma turek'iby'iyi si,",
        "Tukegukir'ibyo mw'ijuru.",
        "Tuboner'imbabazi,",
        "Mur'uyu munsi mwiza.",
        "Dushake kuruhuka,",
        "No ku rurembo rwo mw'ijuru."
      ],
      "number": 1
    }
  ]
}