{
  "number": 394,
  "language": "es",
  "title": "¡Cuan firme cimiento!",
  "stanzas": [
    {
      "type": "verse",
      "lines": [
        "### ¡Cuan firme cimiento!"
      ],
      "number": 1
    },
    {
      "type": "verse",
      "lines": [
        "¡Cuan firme cimiento ha puesto a la",
        "fe",
        "el Padre en su eterna Palabra de",
        "amor!",
        "¿Qué más a su pueblo pudiera",
        "añadir",
        "de lo que en su Libro ha dicho el",
        "Señor,",
        "de lo que en su Libro ha dicho el",
        "Señor?"
      ],
      "number": 2
    },
    {
      "type": "verse",
      "lines": [
        "\"No tengas temor, pues contigo yo",
        "estoy.",
        "Sí, yo soy tu Dios, y te socorreré.",
        "Apoyo, sostén, fortaleza y poder.",
        "Con mi diestra justa yo te salvaré,",
        "con mi diestra justa yo te salvaré."
      ],
      "number": 3
    },
    {
      "type": "verse",
      "lines": [
        "\"Las aguas profundas no te",
        "anegarán,",
        "ni aun cuando cruzares el mar de",
        "aflicción;",
        "pues siempre contigo en tu angustia",
        "andaré,",
        "trocando tus penas en gran",
        "bendición,",
        "trocando tus penas en gran",
        "bendición."
      ],
      "number": 4
    },
    {
      "type": "verse",
      "lines": [
        "\"Si te hallas probado en ardiente",
        "crisol",
        "mi gracia potente tu fe sostendrá;",
        "tan solo la escoria deseo quemar,",
        "y el oro de tu alma más puro saldrá,",
        "y el oro de tu alma más puro",
        "saldrá\"."
      ],
      "number": 5
    }
  ]
}