{
  "number": 49,
  "language": "ki",
  "title": "49. Nguucia Hari We Jesu (NZK 33)",
  "stanzas": [
    {
      "type": "verse",
      "lines": [
        "1.",
        "Nguucia harĩ we, Jesũ mwega; Tũikaranagie mahiinda mothe,",
        "Ngwenda ũnyiite na ũũnũmie; njikarage gĩthũri-inĩ gĩaku,",
        "Njikarage gĩthũri-inĩ gĩaku.",
        "2.",
        "Nguucia harĩ we, ndirĩ kĩĩndũ; ndirĩ indo cia gũkũrutĩra,",
        "O’ theengia ngoro heheenjeku; ũmĩthambie na thakame yaku,",
        "ũmĩthambie na thakame yaku.",
        "3.",
        "Nguucia harĩ we, nduĩke waku; Nĩngeneete nĩgũtiga meehia,",
        "Na ĩkeno ciothe na mwĩtĩĩo; ngwenda O Jesũ ũrĩa waambirwo,",
        "Ngwenda O Jesũ ũrĩa waambirwo.",
        "4.",
        "Nguucia harĩ wee, hiingo ciothe; O kinya nginye kũu igũrũ,",
        "Ngaatũũra kuo na tene; ndĩĩroragĩre ũthiũ ũcio waku,",
        "Ndĩĩroragĩre ũthiũ ũcio waku."
      ],
      "number": 1
    }
  ]
}