{
  "number": 58,
  "language": "ki",
  "title": "58. We Roho Mutheru Ma (NZK 41)",
  "stanzas": [
    {
      "type": "verse",
      "lines": [
        "1.",
        "We Roho Mũtheru ma, We mũtongoria wa ma,",
        "ũtũnyite moko riu rũgendo-ini rũrũ.",
        "Tũigue mũgambo waku, Mũgambo mũhoreri,",
        "“Mũgendi ũka hari nii, ningũgũkinyia mũcii.”",
        "2.",
        "We nowe murata ki, uteithio wa hakuhi",
        "Nina nganja na guoya, Hindi iria twi nduma-inĩ,",
        "Tũigue mũgambo waku, Mũgambo mũhoreri,",
        "“Mũgendi ũka hari nii, ningũgũkinyia mũcii.”",
        "3.",
        "Wira witu wathira, Tũninirwo minoga,",
        "Twiriragirie igũrũ, Na ngatho na mahoya,",
        "Tũigue mũgambo waku, Mũgambo mũhoreri,",
        "“Mũgendi ũka hari nii, ningũgũkinyia mũcii.”"
      ],
      "number": 1
    }
  ]
}