{
  "number": 95,
  "language": "nso",
  "title": " 95 RE BOLOKEGILE BEKENG E NNGWE",
  "stanzas": [
    {
      "type": "verse",
      "lines": [
        "### 95 RE BOLOKEGILE BEKENG E NNGWE",
        "АН 386 CH 462",
        "SAFELY THROUGH ANOTHER WEEK"
      ],
      "number": 1
    },
    {
      "type": "verse",
      "lines": [
        "Re tšwile bekeng e ngwe, Modimo 're tlišitše,",
        "Re nyakeng mašoto, re mo lete lehono,",
        "Letšatši le lebotse, Le bontšha tša ka pele,",
        "Letšatši le lebotse, Le ka pele la bokamoso;"
      ],
      "number": 2
    },
    {
      "type": "verse",
      "lines": [
        "Ge re kgopela mogau, Ka ina la 'Mphološi",
        "Re bontšhe sefahlogo, Tloša dihlong tša rena,",
        "Re lahle tša lefase, Re ikhutše tšatšing lekhwi,",
        "Re lahle tša lefase, Re ikhutše tšatšing lekhwi;"
      ],
      "number": 3
    },
    {
      "type": "verse",
      "lines": [
        "Ge re tlo go tumiša, Re ekwa bo gona bja Gago,",
        "Re bone kgalalelo, Ge re tlile felong go kgethwa,",
        "O re fe Morena, Mošomo o sa felego,",
        "O re fe Morena, Mošomo o sa felego;"
      ],
      "number": 4
    },
    {
      "type": "verse",
      "lines": [
        "A ebangedi ya gago, E phediše bakgethwa,",
        "E fenye le ba babe, E tliše tokologo,",
        "Ka disabata tšohle, Re buse le Morena,",
        "Ka disabata tšohle, Re buse le Morena;"
      ],
      "number": 5
    }
  ]
}