{
  "number": 215,
  "language": "ru",
  "title": "Я хочу, мой Спаситель, любить",
  "stanzas": [
    {
      "type": "verse",
      "lines": [
        "### Я хочу, мой Спаситель, любить"
      ],
      "number": 1
    },
    {
      "type": "verse",
      "lines": [
        "Я хочу, мой Спаситель, любить",
        "Всей душою, всем сердцем Тебя;",
        "Я хочу никогда не забыть,",
        "Как Ты плакал, страдал за меня."
      ],
      "number": 2
    },
    {
      "type": "verse",
      "lines": [
        "Ты в наш мир приходил послужить,",
        "Благодатью навеки спасти;",
        "Ты, за всех нас страдая, просил:",
        "Отче Праведный, грешных прости!"
      ],
      "number": 3
    },
    {
      "type": "verse",
      "lines": [
        "Жить хочу, мой Господь, для Тебя,",
        "Твой Закон свято в жизни блюсти,",
        "Всем хочу возвестить, как, любя,",
        "Восхотел Ты всех грешных спасти."
      ],
      "number": 4
    }
  ]
}