{
  "number": 58,
  "language": "ru",
  "title": "Божий Сын Единородный",
  "stanzas": [
    {
      "type": "verse",
      "lines": [
        "### Божий Сын Единородный"
      ],
      "number": 1
    },
    {
      "type": "verse",
      "lines": [
        "Божий Сын Единородный -",
        "Всей Вселенной Он Творец.",
        "Он есть Альфа и Омега,",
        "Он начало и конец.",
        "Всё, что было, есть и будет, -",
        "Это всё Его любовь.",
        "Ныне и вовек веков! Аминь."
      ],
      "number": 2
    },
    {
      "type": "verse",
      "lines": [
        "О безгрешных воинств сонмы,",
        "Преклонитесь перед Ним!",
        "В восхищении падите",
        "Перед Дивным и Святым!",
        "Неумолчно воспевайте",
        "Бесконечную любовь",
        "Ныне и вовек веков! Аминь."
      ],
      "number": 3
    }
  ]
}